{
	"item_group": "Unterwäsche & Bademode",
	"current_stock_003_halle_altstadt": 0,
	"image": null,
	"creation": "2018-05-07T16:37:07.635774",
	"website_image": null,
	"disabled": 0,
	"current_stock_wh_ludwigsfelde": 0,
	"first_time_ordered_on_": "2018-05-07",
	"ORDERS_7D": null,
	"marketing_text": "Noch mehr Auswahl online",
	"ORDERS_ALLTIME": null,
	"item_name": "Cornalli Unterhosen 2stk Schwartz XXL",
	"level_0_item_group": "Fashion",
	"qrcode_fm02": "https://factorymarket.app.link/TOpTVY79qR?product_id=e2158c3a-3029-49e5-be7c-5b8a3b9f3ee1",
	"is_sales_item": 1,
	"current_stock_002_halle_neustadt": 0,
	"rack_number": null,
	"item_group_level_0": null,
	"base_price_text": "3,99  € je 1 Stück",
	"strike_price": 0,
	"description": "Retro, Schwartz/Schwartz XXL",
	"parent": null,
	"standard_gross_selling_price": 3.99,
	"brand": null,
	"barcode": "0350926665747",
	"item_code": "PP-000008463",
	"current_stock_001_kaufpark_eiche": 0,
	"name": "PP-000008463",
	"_timestamp": "20190122 150229.387",
	"ORDERS_TODAY": null,
	"shelf_number": null,
	"BARCODE": null,
	"ORDERS_YESTERDAY": null,
	"base_price": "3.99",
	"current_gross_selling_price": 1.99,
	"ORDERS_30D": null
}