{
	"item_group": "Getränke",
	"current_stock_003_halle_altstadt": 0,
	"image": "/files/4002221002944.jpg",
	"creation": "2018-05-22T14:22:59.225853",
	"website_image": null,
	"disabled": 0,
	"current_stock_wh_ludwigsfelde": 0,
	"first_time_ordered_on_": null,
	"ORDERS_7D": 1,
	"marketing_text": "Weitere 400.000 Artikel in der App",
	"ORDERS_ALLTIME": 10,
	"item_name": "Messmer Kamille 25 stk",
	"level_0_item_group": "Snacks & Getränke",
	"qrcode_fm02": "https://factorymarket.app.link/TOpTVY79qR?product_id=74660006-86e5-4bce-91c1-638484d31d33",
	"is_sales_item": 1,
	"current_stock_002_halle_neustadt": 0,
	"rack_number": null,
	"item_group_level_0": null,
	"base_price_text": "1.49 € je 1 Stück",
	"strike_price": 0,
	"description": "Messmer Kamille 25 stk",
	"parent": null,
	"standard_gross_selling_price": 1.49,
	"brand": null,
	"barcode": "4002221002944",
	"item_code": "PP-000009026",
	"name": "PP-000009026",
	"current_stock_001_kaufpark_eiche": 6,
	"ORDERS_TODAY": 0,
	"shelf_number": null,
	"BARCODE": "4002221002944",
	"ORDERS_YESTERDAY": 0,
	"base_price": "1.49",
	"current_gross_selling_price": 1.49,
	"ORDERS_30D": 1
}