{
	"current_stock_003_halle_altstadt": 6,
	"image": "/files/4006381511223.jpg",
	"creation": "2018-11-07T12:10:17.393488",
	"website_image": "/files/4006381511223.jpg",
	"disabled": 0,
	"current_stock_wh_ludwigsfelde": 0,
	"first_time_ordered_on_": null,
	"marketing_text": "Mehr Artikel online in der App",
	"item_name": "Tintenroller beFab URBAN SPORTIVE blau",
	"level_0_item_group": "Schreibwaren",
	"qrcode_fm02": "https://factorymarket.app.link/TOpTVY79qR?product_id=158c2cae-646d-409d-81f4-d12522c532d3",
	"is_sales_item": 1,
	"current_stock_002_halle_neustadt": 8,
	"rack_number": null,
	"item_group_level_0": null,
	"base_price_text": "5.99 € je 1 Stück",
	"strike_price": 0,
	"description": "Tintenroller beFab URBAN SPORTIVE blau",
	"parent": null,
	"standard_gross_selling_price": 5.99,
	"brand": null,
	"barcode": "4006381511223",
	"item_code": "PP-000015463",
	"current_stock_001_kaufpark_eiche": 0,
	"name": "PP-000015463",
	"shelf_number": null,
	"item_group": "Stifte",
	"current_gross_selling_price": 5.99,
	"base_price": "5.99"
}