{
	"item_group": "Bücher",
	"current_stock_003_halle_altstadt": 13,
	"image": "/files/4007148019600.jpg",
	"creation": "2018-10-16T17:00:37.808967",
	"website_image": "/files/4007148019600.jpg",
	"disabled": 0,
	"current_stock_wh_ludwigsfelde": 0,
	"first_time_ordered_on_": null,
	"ORDERS_7D": 0,
	"marketing_text": "Mehr Artikel online in der App",
	"ORDERS_ALLTIME": 11,
	"item_name": "Kinderleicht zeichnen",
	"level_0_item_group": "Hobby",
	"qrcode_fm02": "https://factorymarket.app.link/TOpTVY79qR?product_id=21f2a7e2-ab9c-4ead-8981-dcea889b7752",
	"is_sales_item": 1,
	"current_stock_002_halle_neustadt": 11,
	"rack_number": null,
	"item_group_level_0": null,
	"base_price_text": "0.99 € je 1 Stück",
	"strike_price": 0,
	"description": "Kinderleicht zeichnen",
	"parent": null,
	"standard_gross_selling_price": 0.99,
	"brand": null,
	"barcode": "4007148019600",
	"item_code": "PP-000014801",
	"name": "PP-000014801",
	"current_stock_001_kaufpark_eiche": 37,
	"ORDERS_TODAY": 0,
	"shelf_number": null,
	"BARCODE": "4007148019600",
	"ORDERS_YESTERDAY": 0,
	"base_price": "0.99",
	"current_gross_selling_price": 0.99,
	"ORDERS_30D": 5
}