{
	"current_stock_003_halle_altstadt": 24,
	"image": "/files/4008789068439.jpg",
	"creation": "2018-11-15T11:32:57.625373",
	"website_image": "/files/4008789068439.jpg",
	"disabled": 0,
	"current_stock_wh_ludwigsfelde": 78,
	"first_time_ordered_on_": null,
	"marketing_text": "Mehr Artikel online in der App",
	"item_name": "Playmobil Duo Pack Prinzessin und Magd",
	"level_0_item_group": "Spielwaren",
	"qrcode_fm02": "https://factorymarket.app.link/TOpTVY79qR?product_id=592d4bdf-39d2-446e-945d-4e56c167313e",
	"is_sales_item": 1,
	"current_stock_002_halle_neustadt": 21,
	"rack_number": null,
	"item_group_level_0": null,
	"base_price_text": "3.99 € je 1 Stück",
	"strike_price": 0,
	"description": "Playmobil Duo Pack Prinzessin und Magd",
	"parent": null,
	"standard_gross_selling_price": 3.99,
	"brand": null,
	"barcode": "4008789068439",
	"item_code": "PP-000015952",
	"current_stock_001_kaufpark_eiche": 19,
	"name": "PP-000015952",
	"shelf_number": null,
	"item_group": "Spielwaren Mädchen",
	"current_gross_selling_price": 3.99,
	"base_price": "3.99"
}