{
	"item_group": "Autopflege",
	"current_stock_003_halle_altstadt": 19,
	"image": "/files/4010126188014.jpg",
	"creation": "2018-06-25T15:13:59.468461",
	"website_image": null,
	"disabled": 0,
	"current_stock_wh_ludwigsfelde": 20,
	"first_time_ordered_on_": null,
	"ORDERS_7D": 0,
	"marketing_text": "Wecke den Putzteufel in Dir!",
	"ORDERS_ALLTIME": 4,
	"item_name": "Insektenschwamm",
	"level_0_item_group": "Auto",
	"qrcode_fm02": "https://factorymarket.app.link/TOpTVY79qR?product_id=77f07937-dd2e-4bbd-a7c9-2f8827319181",
	"is_sales_item": 1,
	"current_stock_002_halle_neustadt": 60,
	"rack_number": null,
	"item_group_level_0": null,
	"base_price_text": "4.99€ je Stück",
	"strike_price": 0,
	"description": "Insektenschwamm",
	"parent": null,
	"standard_gross_selling_price": 0.69,
	"brand": null,
	"barcode": "4010126188014",
	"item_code": "PP-000009791",
	"name": "PP-000009791",
	"current_stock_001_kaufpark_eiche": 37,
	"ORDERS_TODAY": 0,
	"shelf_number": null,
	"BARCODE": "4010126188014",
	"ORDERS_YESTERDAY": 0,
	"base_price": "4.99",
	"current_gross_selling_price": 4.99,
	"ORDERS_30D": 0
}