{
	"current_stock_003_halle_altstadt": 22,
	"image": "/files/4036014005393.png",
	"creation": "2018-02-13T18:49:54.152864",
	"website_image": "/files/4036014005393.png",
	"disabled": 0,
	"current_stock_wh_ludwigsfelde": 0,
	"first_time_ordered_on_": "2017-11-09",
	"marketing_text": "10 000 Artikel für die, die´s selber machen",
	"item_name": "Wolle - Lisa Premium Dunkel Blau 50gr",
	"level_0_item_group": "Hobby",
	"qrcode_fm02": "https://factorymarket.app.link/TOpTVY79qR?product_id=bc3fa6d0-8134-4fa3-8e55-decf54caaabb",
	"is_sales_item": 1,
	"current_stock_002_halle_neustadt": 20,
	"rack_number": "267, 275",
	"item_group_level_0": null,
	"base_price_text": "0.89 € je 1 Stück",
	"strike_price": 0,
	"description": "Wolle - Lisa Premium 50G Dunkel Blau",
	"parent": null,
	"standard_gross_selling_price": 0.89,
	"brand": null,
	"barcode": "4036014005393",
	"item_code": "PP-000002159",
	"current_stock_001_kaufpark_eiche": 19,
	"name": "PP-000002159",
	"shelf_number": "3",
	"item_group": "Wolle",
	"current_gross_selling_price": 0.89,
	"base_price": "0.89"
}