{
	"current_stock_003_halle_altstadt": 3,
	"image": "/files/4040073016733.jpg",
	"creation": "2018-08-24T13:32:14.815519",
	"website_image": null,
	"disabled": 0,
	"current_stock_wh_ludwigsfelde": 0,
	"first_time_ordered_on_": null,
	"marketing_text": "Weitere 400.000 Artikel in der App",
	"item_name": "Sneaker Socken Jungs 27-30",
	"level_0_item_group": "Fashion",
	"qrcode_fm02": "https://factorymarket.app.link/TOpTVY79qR?product_id=e275fa63-dabf-46ea-9706-c7c3f18038a8",
	"is_sales_item": 1,
	"current_stock_002_halle_neustadt": 4,
	"rack_number": null,
	"item_group_level_0": null,
	"base_price_text": "2,99  € je 1 Stück",
	"strike_price": 0,
	"description": "Sneaker Socken Jungs 27-30",
	"parent": null,
	"standard_gross_selling_price": 2.69,
	"brand": null,
	"barcode": "4040073016733",
	"item_code": "PP-000012800",
	"current_stock_001_kaufpark_eiche": 3,
	"name": "PP-000012800",
	"shelf_number": null,
	"item_group": "Strümpfe",
	"current_gross_selling_price": 1.99,
	"base_price": "2.69"
}