{
	"current_stock_003_halle_altstadt": 0,
	"image": null,
	"creation": "2018-02-14T16:00:26.147366",
	"website_image": null,
	"disabled": 0,
	"current_stock_wh_ludwigsfelde": 0,
	"first_time_ordered_on_": "2018-02-02",
	"marketing_text": "Mehr Küchenaccessoires online",
	"item_name": "Kindertrinkflasche Sponge Bob 500ml",
	"level_0_item_group": "Haushalt",
	"qrcode_fm02": "https://factorymarket.app.link/TOpTVY79qR?product_id=d9257bfa-6919-4a97-8c83-35ea62c4fbfc",
	"is_sales_item": 1,
	"current_stock_002_halle_neustadt": 0,
	"rack_number": null,
	"item_group_level_0": null,
	"base_price_text": "1.99 € je 1 Stück",
	"strike_price": 0,
	"description": "Kindertrinkflasche Sponge Bob 500 Ml",
	"parent": null,
	"standard_gross_selling_price": 1.99,
	"brand": null,
	"barcode": "6294004892981",
	"item_code": "PP-000004125",
	"current_stock_001_kaufpark_eiche": 0,
	"name": "PP-000004125",
	"shelf_number": null,
	"item_group": "Trinkflaschen",
	"current_gross_selling_price": 1.99,
	"base_price": "0.79"
}