{
	"current_stock_003_halle_altstadt": 11,
	"image": "/files/7622210840288.png",
	"creation": "2018-11-01T12:48:02.990148",
	"website_image": "/files/7622210840288.png",
	"disabled": 0,
	"current_stock_wh_ludwigsfelde": 0,
	"first_time_ordered_on_": null,
	"marketing_text": "Alles für die Naschkatzen bei factorymarket",
	"item_name": "Milka Supermario Figur 81gr",
	"level_0_item_group": "Snacks & Getränke",
	"qrcode_fm02": "https://factorymarket.app.link/TOpTVY79qR?product_id=d6c3f850-1a89-46ca-9130-6506cda7c96b",
	"is_sales_item": 1,
	"current_stock_002_halle_neustadt": 1,
	"rack_number": null,
	"item_group_level_0": null,
	"base_price_text": "1.99€ je 1 Stück",
	"strike_price": 3.99,
	"description": "Milka Supermario Figur 81gr",
	"parent": null,
	"standard_gross_selling_price": 3.99,
	"brand": null,
	"barcode": "7622210840288",
	"item_code": "PP-000015055",
	"current_stock_001_kaufpark_eiche": 0,
	"name": "PP-000015055",
	"shelf_number": null,
	"item_group": "Weihnachtsschokolade",
	"current_gross_selling_price": 1.99,
	"base_price": "1.99"
}