{
	"current_stock_003_halle_altstadt": 0,
	"image": "/files/8007315588003.jpg",
	"creation": "2018-06-22T15:27:58.035422",
	"website_image": "/files/8007315588003.jpg",
	"disabled": 0,
	"current_stock_wh_ludwigsfelde": 0,
	"first_time_ordered_on_": null,
	"marketing_text": "Das Abenteuer geht weiter in unserer App",
	"item_name": "Violetta Seifenblasenset 36Stk.",
	"level_0_item_group": "Spielwaren",
	"qrcode_fm02": "https://factorymarket.app.link/TOpTVY79qR?product_id=4cedca50-c712-4ca7-a14a-387536608fa4",
	"is_sales_item": 1,
	"current_stock_002_halle_neustadt": 0,
	"rack_number": null,
	"item_group_level_0": null,
	"base_price_text": "0.39 € je 1 Stück",
	"strike_price": 0,
	"description": "Violetta Seifenblasenset 36Stk.",
	"parent": null,
	"standard_gross_selling_price": 0.39,
	"brand": null,
	"barcode": "8007315588003",
	"item_code": "PP-000010235",
	"current_stock_001_kaufpark_eiche": 4,
	"name": "PP-000010235",
	"shelf_number": null,
	"item_group": "Saisonale Spielwaren",
	"current_gross_selling_price": 0.39,
	"base_price": "0.39"
}