{
	"current_stock_003_halle_altstadt": 41,
	"image": "/files/8711252910161.jpg",
	"creation": "2018-09-18T12:53:14.692930",
	"website_image": "/files/8711252910161.jpg",
	"disabled": 0,
	"current_stock_wh_ludwigsfelde": 72,
	"first_time_ordered_on_": null,
	"marketing_text": "Mehr Artikel online in der App",
	"item_name": "Massband 150cm",
	"level_0_item_group": "Hobby",
	"qrcode_fm02": "https://factorymarket.app.link/TOpTVY79qR?product_id=214b5cb1-b361-4daa-ae11-10b56573f634",
	"is_sales_item": 1,
	"current_stock_002_halle_neustadt": 23,
	"rack_number": null,
	"item_group_level_0": null,
	"base_price_text": "0.59 € je 1 Stück",
	"strike_price": 0,
	"description": "Massband 150cm",
	"parent": null,
	"standard_gross_selling_price": 0.59,
	"brand": null,
	"barcode": "8711252910161",
	"item_code": "PP-000013807",
	"current_stock_001_kaufpark_eiche": 13,
	"name": "PP-000013807",
	"shelf_number": null,
	"item_group": "Bastelbedarf",
	"current_gross_selling_price": 0.59,
	"base_price": "0.59"
}