{
	"item_group": "Küchenhelfer",
	"current_stock_003_halle_altstadt": 14,
	"image": "/files/8711252533186.png",
	"creation": "2018-02-13T18:49:20.641020",
	"website_image": null,
	"disabled": 0,
	"current_stock_wh_ludwigsfelde": 180,
	"first_time_ordered_on_": "2017-11-10",
	"ORDERS_7D": 0,
	"marketing_text": "Weitere 400.000 Artikel in der App",
	"ORDERS_ALLTIME": 76,
	"item_name": "Bestecksatz 16stk",
	"level_0_item_group": "Haushalt",
	"qrcode_fm02": "https://factorymarket.app.link/TOpTVY79qR?product_id=7fa7c43b-3794-4d6b-a7a1-008e6c204ca3",
	"is_sales_item": 1,
	"current_stock_002_halle_neustadt": 15,
	"rack_number": "71",
	"item_group_level_0": null,
	"base_price_text": "7.99 € je 1 Stück",
	"strike_price": 0,
	"description": "Bestecksatz 16St",
	"parent": null,
	"standard_gross_selling_price": 3.99,
	"brand": null,
	"barcode": "8711252533186",
	"item_code": "PP-000000281",
	"name": "PP-000000281",
	"current_stock_001_kaufpark_eiche": 16,
	"ORDERS_TODAY": 0,
	"shelf_number": "1",
	"BARCODE": "8711252533186",
	"ORDERS_YESTERDAY": 0,
	"base_price": "7.99",
	"current_gross_selling_price": 7.99,
	"ORDERS_30D": 4
}