{
	"current_stock_003_halle_altstadt": 0,
	"image": "/files/8711252097206.jpg",
	"creation": "2018-09-18T12:53:06.254004",
	"website_image": "/files/8711252097206.jpg",
	"disabled": 0,
	"current_stock_wh_ludwigsfelde": 0,
	"first_time_ordered_on_": null,
	"marketing_text": "Mehr Artikel online in der App",
	"item_name": "Teller 22cm Blätterdekor",
	"level_0_item_group": "Haushalt",
	"qrcode_fm02": "https://factorymarket.app.link/TOpTVY79qR?product_id=5cf1d3d3-dfa4-40b7-9194-c8486b3f9bbe",
	"is_sales_item": 1,
	"current_stock_002_halle_neustadt": 0,
	"rack_number": null,
	"item_group_level_0": null,
	"base_price_text": "0.79 € je 1 Stück",
	"strike_price": 0,
	"description": "Teller 22cm Blätterdekor",
	"parent": null,
	"standard_gross_selling_price": 0.79,
	"brand": null,
	"barcode": "8711252097206",
	"item_code": "PP-000013765",
	"current_stock_001_kaufpark_eiche": 0,
	"name": "PP-000013765",
	"shelf_number": null,
	"item_group": "Keramik & Porzellan",
	"current_gross_selling_price": 0.79,
	"base_price": "0.79"
}