{
	"item_group": "Weihnachten",
	"current_stock_003_halle_altstadt": 0,
	"image": "/files/8711252486505.jpg",
	"creation": "2018-06-07T12:25:52.383878",
	"website_image": null,
	"disabled": 0,
	"current_stock_wh_ludwigsfelde": 0,
	"first_time_ordered_on_": null,
	"ORDERS_7D": 0,
	"marketing_text": "Tauche ein in die Auswahl von factorymarket!",
	"ORDERS_ALLTIME": 70,
	"item_name": "Lichtschlau Rot 9m",
	"level_0_item_group": "Home & Deko",
	"qrcode_fm02": "https://factorymarket.app.link/TOpTVY79qR?product_id=75376e1a-5def-4365-b482-cf80fb461e16",
	"is_sales_item": 1,
	"current_stock_002_halle_neustadt": 0,
	"rack_number": null,
	"item_group_level_0": null,
	"base_price_text": "1.99€ je 1 Stück",
	"strike_price": 0,
	"description": "Lichtschlau Rot 9m",
	"parent": null,
	"standard_gross_selling_price": 9.99,
	"brand": null,
	"barcode": "8711252486505",
	"item_code": "PP-000009657",
	"name": "PP-000009657",
	"current_stock_001_kaufpark_eiche": 2,
	"ORDERS_TODAY": 0,
	"shelf_number": null,
	"BARCODE": "8711252486505",
	"ORDERS_YESTERDAY": 0,
	"base_price": "9.99",
	"current_gross_selling_price": 1.99,
	"ORDERS_30D": 0
}