{
	"current_stock_003_halle_altstadt": 0,
	"image": "/files/8711252053974.png",
	"creation": "2018-02-13T18:52:06.879176",
	"website_image": "/files/8711252053974.png",
	"disabled": 0,
	"current_stock_wh_ludwigsfelde": 0,
	"first_time_ordered_on_": "2017-11-10",
	"marketing_text": "Alles für den Wuffi & die Mieze",
	"item_name": "Hunde-/Katzennapf 24x6,5cm",
	"level_0_item_group": "Tierbedarf",
	"qrcode_fm02": "https://factorymarket.app.link/TOpTVY79qR?product_id=466fec58-ac0c-46a3-b2e2-fd61b52d71d7",
	"is_sales_item": 1,
	"current_stock_002_halle_neustadt": 0,
	"rack_number": "118",
	"item_group_level_0": null,
	"base_price_text": "0.99 € je 1 Stück",
	"strike_price": 0,
	"description": "Hunde-/Katzennapf 24X6,5Cm",
	"parent": null,
	"standard_gross_selling_price": 0.99,
	"brand": null,
	"barcode": "8711252053974",
	"item_code": "PP-000000081",
	"current_stock_001_kaufpark_eiche": 7,
	"name": "PP-000000081",
	"shelf_number": "3",
	"item_group": "Katzen",
	"current_gross_selling_price": 0.99,
	"base_price": "0.99"
}