{
	"item_group": "Saisonale Spielwaren",
	"current_stock_003_halle_altstadt": 0,
	"image": "/files/8718158064264.jpg",
	"creation": "2018-02-13T19:01:27.368860",
	"website_image": "/files/8718158064264.jpg",
	"disabled": 0,
	"current_stock_wh_ludwigsfelde": 0,
	"first_time_ordered_on_": null,
	"ORDERS_7D": 0,
	"marketing_text": "481.983 weiterer Artikel in unserer App",
	"ORDERS_ALLTIME": 72,
	"item_name": "Strandspielzeug 5-Teilig 4var",
	"level_0_item_group": "Spielwaren",
	"qrcode_fm02": "https://factorymarket.app.link/TOpTVY79qR?product_id=251d2aef-1cf6-41ec-8ff8-709aa8ed7c09",
	"is_sales_item": 1,
	"current_stock_002_halle_neustadt": 0,
	"rack_number": null,
	"item_group_level_0": null,
	"base_price_text": "2.99 € je Set",
	"strike_price": 0,
	"description": "Strandspielzeug 5tlg 4versch. Sorten",
	"parent": null,
	"standard_gross_selling_price": 2.99,
	"brand": null,
	"barcode": "8718158064264",
	"item_code": "PP-000003063",
	"name": "PP-000003063",
	"current_stock_001_kaufpark_eiche": 0,
	"ORDERS_TODAY": 0,
	"shelf_number": null,
	"BARCODE": "8718158064264",
	"ORDERS_YESTERDAY": 0,
	"base_price": "2.99",
	"current_gross_selling_price": 2.99,
	"ORDERS_30D": 0
}