{
	"item_group": "Künstlerbedarf",
	"current_stock_003_halle_altstadt": 14,
	"image": "/files/8719202262636.jpg",
	"creation": "2018-02-28T16:19:01.845318",
	"website_image": null,
	"disabled": 0,
	"current_stock_wh_ludwigsfelde": 42,
	"first_time_ordered_on_": "2018-02-27",
	"ORDERS_7D": 1,
	"marketing_text": "10 000 Artikel für die, die´s selber machen",
	"ORDERS_ALLTIME": 37,
	"item_name": "Farbwanne",
	"level_0_item_group": "Hobby",
	"qrcode_fm02": "https://factorymarket.app.link/TOpTVY79qR?product_id=5962e4b2-8e1c-438c-b4d7-1ca06224218d",
	"is_sales_item": 1,
	"current_stock_002_halle_neustadt": 14,
	"rack_number": null,
	"item_group_level_0": null,
	"base_price_text": "0.99 € je 1 Stück",
	"strike_price": 0,
	"description": "Farbwanne",
	"parent": null,
	"standard_gross_selling_price": 0.99,
	"brand": null,
	"barcode": "8719202262636",
	"item_code": "PP-000005027",
	"name": "PP-000005027",
	"current_stock_001_kaufpark_eiche": 5,
	"ORDERS_TODAY": 0,
	"shelf_number": null,
	"BARCODE": "8719202262636",
	"ORDERS_YESTERDAY": 0,
	"base_price": "0.99",
	"current_gross_selling_price": 0.99,
	"ORDERS_30D": 4
}