{
	"item_group": "Glas",
	"current_stock_003_halle_altstadt": 4,
	"image": "/files/8719202190007.jpg",
	"creation": "2018-02-13T18:52:21.855211",
	"website_image": "/files/8719202190007.jpg",
	"disabled": 0,
	"current_stock_wh_ludwigsfelde": 18,
	"first_time_ordered_on_": "2017-11-01",
	"ORDERS_7D": 8,
	"marketing_text": "Weitere 400.000 Artikel in der App",
	"ORDERS_ALLTIME": 77,
	"item_name": "Kaffe/Teeglas 250ml",
	"level_0_item_group": "Haushalt",
	"qrcode_fm02": "https://factorymarket.app.link/TOpTVY79qR?product_id=044fef12-465a-46e3-9179-033555287a28",
	"is_sales_item": 1,
	"current_stock_002_halle_neustadt": 9,
	"rack_number": "30",
	"item_group_level_0": null,
	"base_price_text": "1.99 € je 1 Stück",
	"strike_price": 0,
	"description": "Kaffe/Teeglas 250Ml",
	"parent": null,
	"standard_gross_selling_price": 1.89,
	"brand": null,
	"barcode": "8719202190007",
	"item_code": "PP-000000989",
	"name": "PP-000000989",
	"current_stock_001_kaufpark_eiche": 8,
	"ORDERS_TODAY": 0,
	"shelf_number": "1",
	"BARCODE": "8719202190007",
	"ORDERS_YESTERDAY": 6,
	"base_price": "1.89",
	"current_gross_selling_price": 1.99,
	"ORDERS_30D": 8
}