{
	"item_group": "Hefte & Blöcke",
	"current_stock_003_halle_altstadt": 6,
	"image": "/files/9783868485943.jpeg",
	"creation": "2018-11-07T12:10:57.486938",
	"website_image": "/files/9783868485943.jpeg",
	"disabled": 0,
	"current_stock_wh_ludwigsfelde": 0,
	"first_time_ordered_on_": null,
	"ORDERS_7D": 0,
	"marketing_text": "Mehr Artikel online in der App",
	"ORDERS_ALLTIME": 13,
	"item_name": "Supermalspass 64 Seiten zum Ausmalen",
	"level_0_item_group": "Schreibwaren",
	"qrcode_fm02": "https://factorymarket.app.link/TOpTVY79qR?product_id=f8a1efc3-8756-4e8b-824d-a2a1e22a37d4",
	"is_sales_item": 1,
	"current_stock_002_halle_neustadt": 1,
	"rack_number": null,
	"item_group_level_0": null,
	"base_price_text": "2.49 € je 1 Stück",
	"strike_price": 0,
	"description": "Supermalspass 64 Seiten zum Ausmalen",
	"parent": null,
	"standard_gross_selling_price": 2.49,
	"brand": null,
	"barcode": "9783868485943",
	"item_code": "PP-000015706",
	"name": "PP-000015706",
	"current_stock_001_kaufpark_eiche": 0,
	"ORDERS_TODAY": 0,
	"shelf_number": null,
	"BARCODE": "9783868485943",
	"ORDERS_YESTERDAY": 0,
	"base_price": "2.49",
	"current_gross_selling_price": 2.49,
	"ORDERS_30D": 0
}